{
  "2025-05-01": {
    "cartoon": [
      {
        "start": "00:00",
        "end": "23:59",
        "title": "Teste de Programação",
        "desc": "Este bloco cobre o dia todo para testes."
      }
    ],
    "disckds": [
      {
        "start": "00:00",
        "end": "23:59",
        "title": "Teste de Programação",
        "desc": "Este bloco cobre o dia todo para testes."
      }
    ],
    "disneychan": [
      {
        "start": "00:00",
        "end": "23:59",
        "title": "Teste de Programação",
        "desc": "Este bloco cobre o dia todo para testes."
      }
    ],
    "gloob": [
      {
        "start": "00:00",
        "end": "23:59",
        "title": "Teste de Programação",
        "desc": "Este bloco cobre o dia todo para testes."
      }
    ],
    "nickjr": [
      {
        "start": "00:00",
        "end": "23:59",
        "title": "Teste de Programação",
        "desc": "Este bloco cobre o dia todo para testes."
      }
    ],
    "nickelodeon": [
      {
        "start": "00:00",
        "end": "23:59",
        "title": "Teste de Programação",
        "desc": "Este bloco cobre o dia todo para testes."
      }
    ]
  }
}